myl.py
myl-0.9.8.dist-info/licenses/LICENSE
myl-0.9.8.dist-info/METADATA
myl-0.9.8.dist-info/WHEEL
myl-0.9.8.dist-info/entry_points.txt
myl-0.9.8.dist-info/top_level.txt
myl-0.9.8.dist-info/RECORD
