Metadata-Version: 2.4
Name: myl
Version: 0.9.8
Summary: Dead simple IMAP CLI client
Author-email: Philipp Schmitt <philipp@schmitt.co>
License:                     GNU GENERAL PUBLIC LICENSE
Project-URL: homepage, https://github.com/pschmitt/myl
Project-URL: documentation, https://github.com/pschmitt/myl/blob/head/readme.md
Project-URL: repository, https://github.com/pschmitt/myl
Project-URL: issues, https://github.com/pschmitt/myl/issues
Keywords: imap,email
Classifier: Programming Language :: Python :: 3
Requires-Python: >=3.8
License-File: LICENSE
Requires-Dist: imap-tools<2.0.0,>=1.5.0
Requires-Dist: myl-discovery>=0.6.4
Requires-Dist: rich<15.0.0,>=13.0.0
Requires-Dist: html2text>=2024.2.26
Dynamic: license-file
